pamm/.gitignore
pamm/__init__.py
pamm/algorithms/__init__.py
pamm/algorithms/base_model.py
pamm/algorithms/cross_validation.py
pamm/algorithms/regression/__init__.py
pamm/algorithms/regression/cvmodel/__init__.py
pamm/algorithms/regression/cvmodel/cv_model.py
pamm/algorithms/regression/gradient_boost/pgd_regression.py
pamm/algorithms/regression/gradient_boost/sgd_regression.py
pamm/algorithms/regression/gradient_boost/simple_gradient.py
pamm/algorithms/regression/iterations_regression.py
pamm/algorithms/regression/jackknife_model.py
pamm/algorithms/regression/qp_mls_model.py
pamm/algorithms/regression/regression_model.py
pamm/algorithms/regression/regularization/elastic_net.py
pamm/algorithms/regression/regularization/lasso_model.py
pamm/algorithms/regression/regularization/ridge_model.py
pamm/algorithms/regression/tsls_model.py
pamm/algorithms/regression/wls/mls_model.py
pamm/algorithms/regression/wls/qp_model.py
pamm/algorithms/regression/wls/wls_model.py
pamm/algorithms/regression/wls/wtsls_model.py
pamm/algorithms/weighing/weights_data_algorithms.py
pamm/algorithms/weighing/weigts_beta_algorithms.py
pamm/metricks/__init__.py
pamm/metricks/numeric.py
pamm/poetry.lock
pamm/preprocessing/__init__.py
pamm/preprocessing/filters/__init__.py
pamm/preprocessing/filters/number.py
pamm/preprocessing/filters/times.py
pamm/preprocessing/merge.py
pamm/pyproject.toml
pamm/README.md
pamm-0.2.2.dist-info/METADATA
pamm-0.2.2.dist-info/WHEEL
pamm-0.2.2.dist-info/RECORD
