Metadata-Version: 2.3
Name: pamm
Version: 0.2.2
Summary: Processing analyze merge machine learning.
Author: Alexeebitch
Author-email: rmrs1@yandex.ru
Requires-Python: >=3.10.0,<4.0.0
Classifier: Programming Language :: Python :: 3
Classifier: Programming Language :: Python :: 3.10
Classifier: Programming Language :: Python :: 3.11
Classifier: Programming Language :: Python :: 3.12
Classifier: Programming Language :: Python :: 3.13
Requires-Dist: cvxopt (>=1.3.2,<2.0.0)
Requires-Dist: numpy (>=2.2.3,<3.0.0)
